navalmartin_mir_aws_utils/__init__.py
navalmartin_mir_aws_utils/aws_credentials.py
navalmartin_mir_aws_utils/boto3_client.py
navalmartin_mir_aws_utils/cognito_idp_utils.py
navalmartin_mir_aws_utils/exceptions.py
navalmartin_mir_aws_utils/file_s3_batch.py
navalmartin_mir_aws_utils/s3_utils.py
navalmartin_mir_aws_utils/sqs_queue_config.py
navalmartin_mir_aws_utils/sqs_utils.py
navalmartin_mir_aws_utils/examples/__init__.py
navalmartin_mir_aws_utils/examples/create_image_batch.py
navalmartin_mir_aws_utils/examples/create_sagemaker_model.py
navalmartin_mir_aws_utils/examples/lamda_task_decorator.py
navalmartin_mir_aws_utils/examples/working_with_cognito.py
navalmartin_mir_aws_utils/examples/working_with_s3.py
navalmartin_mir_aws_utils/examples/working_with_secrets_manager.py
navalmartin_mir_aws_utils/examples/working_with_ses.py
navalmartin_mir_aws_utils/examples/working_with_sqs.py
navalmartin_mir_aws_utils/examples/working_with_state_functions.py
navalmartin_mir_aws_utils/tasks/__init__.py
navalmartin_mir_aws_utils/tasks/ses_tasks/__init__.py
navalmartin_mir_aws_utils/tasks/ses_tasks/ses_tasks.py
navalmartin_mir_aws_utils/tasks_lambdas/__init__.py
navalmartin_mir_aws_utils/tasks_lambdas/aws_tasks_decorator.py
navalmartin_mir_aws_utils/utils/__init__.py
navalmartin_mir_aws_utils/utils/cognito_user_data.py
navalmartin_mir_aws_utils/utils/sfn_utils.py
navalmartin_mir_aws_utils/utils/simple_email.py
navalmartin_mir_aws_utils/utils/utils.py
navalmartin_mir_aws_utils-0.0.36.dist-info/METADATA
navalmartin_mir_aws_utils-0.0.36.dist-info/WHEEL
navalmartin_mir_aws_utils-0.0.36.dist-info/licenses/LICENSE
navalmartin_mir_aws_utils-0.0.36.dist-info/RECORD
