Metadata-Version: 2.1
Name: navalmartin_mir_aws_utils
Version: 0.0.36
Summary: Various utilities for working with AWS in Python 3. for the mir project
Project-URL: Homepage, https://github.com/Navalmartin/navalmartin_mir_aws_utils
Project-URL: Bug Tracker, https://github.com/Navalmartin/navalmartin_mir_aws_utils/issues
Author-email: Alexandros Giavaras <a.giavaras@gmail.com>
License-File: LICENSE
Classifier: License :: OSI Approved :: MIT License
Classifier: Operating System :: OS Independent
Classifier: Programming Language :: Python :: 3
Requires-Python: >=3.7
